pyhexdump/__init__.py
pyhexdump/pyhexdump.py
pyhexdump-0.5.1.dist-info/entry_points.txt
pyhexdump-0.5.1.dist-info/LICENSE
pyhexdump-0.5.1.dist-info/WHEEL
pyhexdump-0.5.1.dist-info/METADATA
pyhexdump-0.5.1.dist-info/RECORD
